<?xml version = '1.0' encoding = 'UTF-8'?>
<Relation class="oracle.dbtools.crest.model.design.logical.Relation" name="SALES_DELIVERY_COMPANY_FK" directorySegmentName="seg_0" id="0E4AC3A6-E45F-BFE8-E9F5-48F53F6A619C">
<createdBy>nserus</createdBy>
<createdTime>2021-05-05 11:10:34 UTC</createdTime>
<generatorID>FE71A2E8-8BB0-3500-04D1-03AA0D3B0BB3</generatorID>
<ownerDesignName>StarModel</ownerDesignName>
<engineerTo>
<item key="7E31CA19-BD02-7AD3-624A-3CBC373124CA" value="true"/>
</engineerTo>
<sourcePk>8A3C59E9-DDE7-9AD4-C4B3-A90EC57848AD</sourcePk>
<identifying>false</identifying>
<optionalSource>true</optionalSource>
<optionalTarget>false</optionalTarget>
<sourceCardinality>1</sourceCardinality>
<sourceEntity>2ED898A7-575E-BB0B-2D4B-9985C312B9D8</sourceEntity>
<targetCardinalityString>*</targetCardinalityString>
<targetEntity>FC78D0FF-1CEC-A1B5-3044-DB9014D8B73C</targetEntity>
<transferable>true</transferable>
<deleteRule>NO ACTION</deleteRule>
</Relation>
